{
	"info": {
		"_postman_id": "fdc0ceb2-b218-4e9c-8cb1-cd062c2c37d4",
		"name": "EMS API collection",
		"description": "API for my project",
		"schema": "https://schema.getpostman.com/json/collection/v2.1.0/collection.json",
		"_exporter_id": "20989510"
	},
	"item": [
		{
			"name": "api",
			"item": [
				{
					"name": "auth",
					"item": [
						{
							"name": "login",
							"item": [
								{
									"name": "api auth login create",
									"request": {
										"auth": {
											"type": "noauth"
										},
										"method": "POST",
										"header": [
											{
												"key": "Content-Type",
												"value": "application/json"
											}
										],
										"body": {
											"mode": "raw",
											"raw": "{\n  \"password\": \"string\",\n  \"username\": \"string\"\n}",
											"options": {
												"raw": {
													"headerFamily": "json",
													"language": "json"
												}
											}
										},
										"url": {
											"raw": "{{baseUrl}}/api/auth/login/",
											"host": [
												"{{baseUrl}}"
											],
											"path": [
												"api",
												"auth",
												"login",
												""
											]
										},
										"description": "Takes a set of user credentials and returns an access and refresh JSON web\ntoken pair to prove the authentication of those credentials."
									},
									"response": [
										{
											"name": "No response body",
											"originalRequest": {
												"method": "POST",
												"header": [
													{
														"key": "Content-Type",
														"value": "application/json"
													}
												],
												"body": {
													"mode": "raw",
													"raw": "{\n  \"password\": \"string\",\n  \"username\": \"string\"\n}",
													"options": {
														"raw": {
															"headerFamily": "json",
															"language": "json"
														}
													}
												},
												"url": {
													"raw": "{{baseUrl}}/api/auth/login/",
													"host": [
														"{{baseUrl}}"
													],
													"path": [
														"api",
														"auth",
														"login",
														""
													]
												}
											},
											"status": "OK",
											"code": 200,
											"_postman_previewlanguage": "text",
											"header": [],
											"cookie": [],
											"body": ""
										}
									]
								}
							]
						},
						{
							"name": "password",
							"item": [
								{
									"name": "update",
									"item": [
										{
											"name": "api auth password update update",
											"request": {
												"auth": {
													"type": "bearer",
													"bearer": [
														{
															"key": "token",
															"value": "{{bearerToken}}",
															"type": "string"
														}
													]
												},
												"method": "PUT",
												"header": [
													{
														"key": "Content-Type",
														"value": "application/json"
													}
												],
												"body": {
													"mode": "raw",
													"raw": "{\n  \"new_password\": \"string\",\n  \"old_password\": \"string\"\n}",
													"options": {
														"raw": {
															"headerFamily": "json",
															"language": "json"
														}
													}
												},
												"url": {
													"raw": "{{baseUrl}}/api/auth/password/update/",
													"host": [
														"{{baseUrl}}"
													],
													"path": [
														"api",
														"auth",
														"password",
														"update",
														""
													]
												}
											},
											"response": [
												{
													"name": "No response body",
													"originalRequest": {
														"method": "PUT",
														"header": [
															{
																"key": "Content-Type",
																"value": "application/json"
															},
															{
																"key": "Authorization",
																"value": "Bearer <token>",
																"description": "Added as a part of security scheme: bearer"
															}
														],
														"body": {
															"mode": "raw",
															"raw": "{\n  \"new_password\": \"string\",\n  \"old_password\": \"string\"\n}",
															"options": {
																"raw": {
																	"headerFamily": "json",
																	"language": "json"
																}
															}
														},
														"url": {
															"raw": "{{baseUrl}}/api/auth/password/update/",
															"host": [
																"{{baseUrl}}"
															],
															"path": [
																"api",
																"auth",
																"password",
																"update",
																""
															]
														}
													},
													"status": "OK",
													"code": 200,
													"_postman_previewlanguage": "text",
													"header": [],
													"cookie": [],
													"body": ""
												}
											]
										},
										{
											"name": "api auth password update partial update",
											"request": {
												"auth": {
													"type": "bearer",
													"bearer": [
														{
															"key": "token",
															"value": "{{bearerToken}}",
															"type": "string"
														}
													]
												},
												"method": "PATCH",
												"header": [
													{
														"key": "Content-Type",
														"value": "application/json"
													}
												],
												"body": {
													"mode": "raw",
													"raw": "{\n  \"old_password\": \"string\",\n  \"new_password\": \"string\"\n}",
													"options": {
														"raw": {
															"headerFamily": "json",
															"language": "json"
														}
													}
												},
												"url": {
													"raw": "{{baseUrl}}/api/auth/password/update/",
													"host": [
														"{{baseUrl}}"
													],
													"path": [
														"api",
														"auth",
														"password",
														"update",
														""
													]
												}
											},
											"response": [
												{
													"name": "No response body",
													"originalRequest": {
														"method": "PATCH",
														"header": [
															{
																"key": "Content-Type",
																"value": "application/json"
															},
															{
																"key": "Authorization",
																"value": "Bearer <token>",
																"description": "Added as a part of security scheme: bearer"
															}
														],
														"body": {
															"mode": "raw",
															"raw": "{\n  \"old_password\": \"string\",\n  \"new_password\": \"string\"\n}",
															"options": {
																"raw": {
																	"headerFamily": "json",
																	"language": "json"
																}
															}
														},
														"url": {
															"raw": "{{baseUrl}}/api/auth/password/update/",
															"host": [
																"{{baseUrl}}"
															],
															"path": [
																"api",
																"auth",
																"password",
																"update",
																""
															]
														}
													},
													"status": "OK",
													"code": 200,
													"_postman_previewlanguage": "text",
													"header": [],
													"cookie": [],
													"body": ""
												}
											]
										}
									]
								}
							]
						},
						{
							"name": "profile",
							"item": [
								{
									"name": "update",
									"item": [
										{
											"name": "api auth profile update update",
											"request": {
												"auth": {
													"type": "bearer",
													"bearer": [
														{
															"key": "token",
															"value": "{{bearerToken}}",
															"type": "string"
														}
													]
												},
												"method": "PUT",
												"header": [
													{
														"key": "Content-Type",
														"value": "application/json"
													},
													{
														"key": "Accept",
														"value": "application/json"
													}
												],
												"body": {
													"mode": "raw",
													"raw": "{\n  \"username\": \"3_GQEmoB\",\n  \"email\": \"az0lb@PrWJOaolzQrAOJ.zc\"\n}",
													"options": {
														"raw": {
															"headerFamily": "json",
															"language": "json"
														}
													}
												},
												"url": {
													"raw": "{{baseUrl}}/api/auth/profile/update/",
													"host": [
														"{{baseUrl}}"
													],
													"path": [
														"api",
														"auth",
														"profile",
														"update",
														""
													]
												}
											},
											"response": [
												{
													"name": "Untitled Response",
													"originalRequest": {
														"method": "PUT",
														"header": [
															{
																"key": "Content-Type",
																"value": "application/json"
															},
															{
																"key": "Accept",
																"value": "application/json"
															},
															{
																"key": "Authorization",
																"value": "Bearer <token>",
																"description": "Added as a part of security scheme: bearer"
															}
														],
														"body": {
															"mode": "raw",
															"raw": "{\n  \"username\": \"3_GQEmoB\",\n  \"email\": \"az0lb@PrWJOaolzQrAOJ.zc\"\n}",
															"options": {
																"raw": {
																	"headerFamily": "json",
																	"language": "json"
																}
															}
														},
														"url": {
															"raw": "{{baseUrl}}/api/auth/profile/update/",
															"host": [
																"{{baseUrl}}"
															],
															"path": [
																"api",
																"auth",
																"profile",
																"update",
																""
															]
														}
													},
													"status": "OK",
													"code": 200,
													"_postman_previewlanguage": "json",
													"header": [
														{
															"key": "Content-Type",
															"value": "application/json"
														}
													],
													"cookie": [],
													"body": "{\n  \"username\": \"oYCKyrpO+7\",\n  \"email\": \"chv566QLgXf@HajNwJWStEBXmwrcJxssyVCZbrzQi.yqb\"\n}"
												}
											]
										},
										{
											"name": "api auth profile update partial update",
											"request": {
												"auth": {
													"type": "bearer",
													"bearer": [
														{
															"key": "token",
															"value": "{{bearerToken}}",
															"type": "string"
														}
													]
												},
												"method": "PATCH",
												"header": [
													{
														"key": "Content-Type",
														"value": "application/json"
													},
													{
														"key": "Accept",
														"value": "application/json"
													}
												],
												"body": {
													"mode": "raw",
													"raw": "{\n  \"username\": \"pA\",\n  \"email\": \"ObzkGv3@ilapKBUhGfyNoPhaXBzjBUus.ip\"\n}",
													"options": {
														"raw": {
															"headerFamily": "json",
															"language": "json"
														}
													}
												},
												"url": {
													"raw": "{{baseUrl}}/api/auth/profile/update/",
													"host": [
														"{{baseUrl}}"
													],
													"path": [
														"api",
														"auth",
														"profile",
														"update",
														""
													]
												}
											},
											"response": [
												{
													"name": "Untitled Response",
													"originalRequest": {
														"method": "PATCH",
														"header": [
															{
																"key": "Content-Type",
																"value": "application/json"
															},
															{
																"key": "Accept",
																"value": "application/json"
															},
															{
																"key": "Authorization",
																"value": "Bearer <token>",
																"description": "Added as a part of security scheme: bearer"
															}
														],
														"body": {
															"mode": "raw",
															"raw": "{\n  \"username\": \"pA\",\n  \"email\": \"ObzkGv3@ilapKBUhGfyNoPhaXBzjBUus.ip\"\n}",
															"options": {
																"raw": {
																	"headerFamily": "json",
																	"language": "json"
																}
															}
														},
														"url": {
															"raw": "{{baseUrl}}/api/auth/profile/update/",
															"host": [
																"{{baseUrl}}"
															],
															"path": [
																"api",
																"auth",
																"profile",
																"update",
																""
															]
														}
													},
													"status": "OK",
													"code": 200,
													"_postman_previewlanguage": "json",
													"header": [
														{
															"key": "Content-Type",
															"value": "application/json"
														}
													],
													"cookie": [],
													"body": "{\n  \"username\": \"oYCKyrpO+7\",\n  \"email\": \"chv566QLgXf@HajNwJWStEBXmwrcJxssyVCZbrzQi.yqb\"\n}"
												}
											]
										}
									]
								},
								{
									"name": "api auth profile retrieve",
									"request": {
										"auth": {
											"type": "bearer",
											"bearer": [
												{
													"key": "token",
													"value": "{{bearerToken}}",
													"type": "string"
												}
											]
										},
										"method": "GET",
										"header": [
											{
												"key": "Accept",
												"value": "application/json"
											}
										],
										"url": {
											"raw": "{{baseUrl}}/api/auth/profile/",
											"host": [
												"{{baseUrl}}"
											],
											"path": [
												"api",
												"auth",
												"profile",
												""
											]
										}
									},
									"response": [
										{
											"name": "Untitled Response",
											"originalRequest": {
												"method": "GET",
												"header": [
													{
														"key": "Accept",
														"value": "application/json"
													},
													{
														"key": "Authorization",
														"value": "Bearer <token>",
														"description": "Added as a part of security scheme: bearer"
													}
												],
												"url": {
													"raw": "{{baseUrl}}/api/auth/profile/",
													"host": [
														"{{baseUrl}}"
													],
													"path": [
														"api",
														"auth",
														"profile",
														""
													]
												}
											},
											"status": "OK",
											"code": 200,
											"_postman_previewlanguage": "json",
											"header": [
												{
													"key": "Content-Type",
													"value": "application/json"
												}
											],
											"cookie": [],
											"body": "{\n  \"id\": 5125,\n  \"username\": \"7dGI\",\n  \"email\": \"LK5foePo9nA@fqetFTWDdmpzbLZTfVYBpaZbsjSan.ty\",\n  \"first_name\": \"string\",\n  \"last_name\": \"string\"\n}"
										}
									]
								}
							]
						},
						{
							"name": "register",
							"item": [
								{
									"name": "api auth register create",
									"request": {
										"auth": {
											"type": "bearer",
											"bearer": [
												{
													"key": "token",
													"value": "{{bearerToken}}",
													"type": "string"
												}
											]
										},
										"method": "POST",
										"header": [
											{
												"key": "Content-Type",
												"value": "application/json"
											},
											{
												"key": "Accept",
												"value": "application/json"
											}
										],
										"body": {
											"mode": "raw",
											"raw": "{\n  \"password\": \"stringstring\",\n  \"username\": \"Nn\",\n  \"email\": \"SeEQ0URPzZLazKI@eYcNsjZUklMNyCauiFbLllFUhWAS.fdg\"\n}",
											"options": {
												"raw": {
													"headerFamily": "json",
													"language": "json"
												}
											}
										},
										"url": {
											"raw": "{{baseUrl}}/api/auth/register/",
											"host": [
												"{{baseUrl}}"
											],
											"path": [
												"api",
												"auth",
												"register",
												""
											]
										}
									},
									"response": [
										{
											"name": "Untitled Response",
											"originalRequest": {
												"method": "POST",
												"header": [
													{
														"key": "Content-Type",
														"value": "application/json"
													},
													{
														"key": "Accept",
														"value": "application/json"
													},
													{
														"key": "Authorization",
														"value": "Bearer <token>",
														"description": "Added as a part of security scheme: bearer"
													}
												],
												"body": {
													"mode": "raw",
													"raw": "{\n  \"password\": \"stringstring\",\n  \"username\": \"Nn\",\n  \"email\": \"SeEQ0URPzZLazKI@eYcNsjZUklMNyCauiFbLllFUhWAS.fdg\"\n}",
													"options": {
														"raw": {
															"headerFamily": "json",
															"language": "json"
														}
													}
												},
												"url": {
													"raw": "{{baseUrl}}/api/auth/register/",
													"host": [
														"{{baseUrl}}"
													],
													"path": [
														"api",
														"auth",
														"register",
														""
													]
												}
											},
											"status": "Created",
											"code": 201,
											"_postman_previewlanguage": "json",
											"header": [
												{
													"key": "Content-Type",
													"value": "application/json"
												}
											],
											"cookie": [],
											"body": "{\n  \"username\": \"oYCKyrpO+7\",\n  \"email\": \"chv566QLgXf@HajNwJWStEBXmwrcJxssyVCZbrzQi.yqb\"\n}"
										}
									]
								}
							]
						},
						{
							"name": "token",
							"item": [
								{
									"name": "refresh",
									"item": [
										{
											"name": "api auth token refresh create",
											"request": {
												"method": "POST",
												"header": [
													{
														"key": "Content-Type",
														"value": "application/json"
													},
													{
														"key": "Accept",
														"value": "application/json"
													}
												],
												"body": {
													"mode": "raw",
													"raw": "{\n  \"refresh\": \"string\"\n}",
													"options": {
														"raw": {
															"headerFamily": "json",
															"language": "json"
														}
													}
												},
												"url": {
													"raw": "{{baseUrl}}/api/auth/token/refresh/",
													"host": [
														"{{baseUrl}}"
													],
													"path": [
														"api",
														"auth",
														"token",
														"refresh",
														""
													]
												},
												"description": "Takes a refresh type JSON web token and returns an access type JSON web\ntoken if the refresh token is valid."
											},
											"response": [
												{
													"name": "Untitled Response",
													"originalRequest": {
														"method": "POST",
														"header": [
															{
																"key": "Content-Type",
																"value": "application/json"
															},
															{
																"key": "Accept",
																"value": "application/json"
															}
														],
														"body": {
															"mode": "raw",
															"raw": "{\n  \"refresh\": \"string\"\n}",
															"options": {
																"raw": {
																	"headerFamily": "json",
																	"language": "json"
																}
															}
														},
														"url": {
															"raw": "{{baseUrl}}/api/auth/token/refresh/",
															"host": [
																"{{baseUrl}}"
															],
															"path": [
																"api",
																"auth",
																"token",
																"refresh",
																""
															]
														}
													},
													"status": "OK",
													"code": 200,
													"_postman_previewlanguage": "json",
													"header": [
														{
															"key": "Content-Type",
															"value": "application/json"
														}
													],
													"cookie": [],
													"body": "{\n  \"access\": \"string\"\n}"
												}
											]
										}
									]
								}
							]
						}
					]
				},
				{
					"name": "dynamic",
					"item": [
						{
							"name": "fields",
							"item": [
								{
									"name": "api dynamic fields retrieve",
									"request": {
										"auth": {
											"type": "bearer",
											"bearer": [
												{
													"key": "token",
													"value": "{{bearerToken}}",
													"type": "string"
												}
											]
										},
										"method": "GET",
										"header": [],
										"url": {
											"raw": "{{baseUrl}}/api/dynamic/fields/",
											"host": [
												"{{baseUrl}}"
											],
											"path": [
												"api",
												"dynamic",
												"fields",
												""
											]
										}
									},
									"response": [
										{
											"name": "No response body",
											"originalRequest": {
												"method": "GET",
												"header": [
													{
														"key": "Authorization",
														"value": "Bearer <token>",
														"description": "Added as a part of security scheme: bearer"
													}
												],
												"url": {
													"raw": "{{baseUrl}}/api/dynamic/fields/",
													"host": [
														"{{baseUrl}}"
													],
													"path": [
														"api",
														"dynamic",
														"fields",
														""
													]
												}
											},
											"status": "OK",
											"code": 200,
											"_postman_previewlanguage": "json",
											"header": [
												{
													"key": "Content-Type",
													"value": "application/json",
													"name": "Content-Type",
													"description": "",
													"type": "text"
												}
											],
											"cookie": [],
											"body": "[\n    \"string\",\n    \"string\",\n    \"string\",\n    \"string\",\n    \"string\"\n]"
										}
									]
								}
							]
						}
					]
				},
				{
					"name": "employee",
					"item": [
						{
							"name": "{id}",
							"item": [
								{
									"name": "api employee retrieve",
									"request": {
										"auth": {
											"type": "bearer",
											"bearer": [
												{
													"key": "token",
													"value": "{{bearerToken}}",
													"type": "string"
												}
											]
										},
										"method": "GET",
										"header": [
											{
												"key": "Accept",
												"value": "application/json"
											}
										],
										"url": {
											"raw": "{{baseUrl}}/api/employee/:id/",
											"host": [
												"{{baseUrl}}"
											],
											"path": [
												"api",
												"employee",
												":id",
												""
											],
											"variable": [
												{
													"key": "id",
													"value": "8519",
													"description": "(Required) "
												}
											]
										}
									},
									"response": [
										{
											"name": "Untitled Response",
											"originalRequest": {
												"method": "GET",
												"header": [
													{
														"key": "Accept",
														"value": "application/json"
													},
													{
														"key": "Authorization",
														"value": "Bearer <token>",
														"description": "Added as a part of security scheme: bearer"
													}
												],
												"url": {
													"raw": "{{baseUrl}}/api/employee/:id/",
													"host": [
														"{{baseUrl}}"
													],
													"path": [
														"api",
														"employee",
														":id",
														""
													],
													"variable": [
														{
															"key": "id"
														}
													]
												}
											},
											"status": "OK",
											"code": 200,
											"_postman_previewlanguage": "json",
											"header": [
												{
													"key": "Content-Type",
													"value": "application/json"
												}
											],
											"cookie": [],
											"body": "{\n  \"fields\": [\n    {\n      \"field_type\": \"s\",\n      \"field_type_name\": \"string\",\n      \"form_field\": 8132,\n      \"label\": \"string\",\n      \"order\": 7990,\n      \"placeholder\": \"string\",\n      \"required\": false,\n      \"value\": \"string\"\n    },\n    {\n      \"field_type\": \"string\",\n      \"field_type_name\": \"string\",\n      \"form_field\": 5410,\n      \"label\": \"string\",\n      \"order\": 3082,\n      \"placeholder\": \"string\",\n      \"required\": false,\n      \"value\": \"string\"\n    }\n  ],\n  \"form_id\": 4667,\n  \"id\": 8594\n}"
										}
									]
								},
								{
									"name": "api employee update",
									"request": {
										"auth": {
											"type": "bearer",
											"bearer": [
												{
													"key": "token",
													"value": "{{bearerToken}}",
													"type": "string"
												}
											]
										},
										"method": "PUT",
										"header": [
											{
												"key": "Content-Type",
												"value": "application/json"
											},
											{
												"key": "Accept",
												"value": "application/json"
											}
										],
										"body": {
											"mode": "raw",
											"raw": "{\n  \"fields\": [\n    {\n      \"form_field\": 1886,\n      \"value\": \"string\"\n    },\n    {\n      \"form_field\": 3853,\n      \"value\": \"string\"\n    }\n  ]\n}",
											"options": {
												"raw": {
													"headerFamily": "json",
													"language": "json"
												}
											}
										},
										"url": {
											"raw": "{{baseUrl}}/api/employee/:id/",
											"host": [
												"{{baseUrl}}"
											],
											"path": [
												"api",
												"employee",
												":id",
												""
											],
											"variable": [
												{
													"key": "id",
													"value": "8519",
													"description": "(Required) "
												}
											]
										}
									},
									"response": [
										{
											"name": "Untitled Response",
											"originalRequest": {
												"method": "PUT",
												"header": [
													{
														"key": "Content-Type",
														"value": "application/json"
													},
													{
														"key": "Accept",
														"value": "application/json"
													},
													{
														"key": "Authorization",
														"value": "Bearer <token>",
														"description": "Added as a part of security scheme: bearer"
													}
												],
												"body": {
													"mode": "raw",
													"raw": "{\n  \"fields\": [\n    {\n      \"form_field\": 1886,\n      \"value\": \"string\"\n    },\n    {\n      \"form_field\": 3853,\n      \"value\": \"string\"\n    }\n  ]\n}",
													"options": {
														"raw": {
															"headerFamily": "json",
															"language": "json"
														}
													}
												},
												"url": {
													"raw": "{{baseUrl}}/api/employee/:id/",
													"host": [
														"{{baseUrl}}"
													],
													"path": [
														"api",
														"employee",
														":id",
														""
													],
													"variable": [
														{
															"key": "id"
														}
													]
												}
											},
											"status": "OK",
											"code": 200,
											"_postman_previewlanguage": "json",
											"header": [
												{
													"key": "Content-Type",
													"value": "application/json"
												}
											],
											"cookie": [],
											"body": "{\n  \"fields\": [\n    {\n      \"field_type\": \"s\",\n      \"field_type_name\": \"string\",\n      \"form_field\": 8132,\n      \"label\": \"string\",\n      \"order\": 7990,\n      \"placeholder\": \"string\",\n      \"required\": false,\n      \"value\": \"string\"\n    },\n    {\n      \"field_type\": \"string\",\n      \"field_type_name\": \"string\",\n      \"form_field\": 5410,\n      \"label\": \"string\",\n      \"order\": 3082,\n      \"placeholder\": \"string\",\n      \"required\": false,\n      \"value\": \"string\"\n    }\n  ],\n  \"form_id\": 4667,\n  \"id\": 8594\n}"
										}
									]
								},
								{
									"name": "api employee partial update",
									"request": {
										"auth": {
											"type": "bearer",
											"bearer": [
												{
													"key": "token",
													"value": "{{bearerToken}}",
													"type": "string"
												}
											]
										},
										"method": "PATCH",
										"header": [
											{
												"key": "Content-Type",
												"value": "application/json"
											},
											{
												"key": "Accept",
												"value": "application/json"
											}
										],
										"body": {
											"mode": "raw",
											"raw": "{\n  \"fields\": [\n    {\n      \"form_field\": 1000,\n      \"value\": \"string\"\n    },\n    {\n      \"form_field\": 4784,\n      \"value\": \"string\"\n    }\n  ]\n}",
											"options": {
												"raw": {
													"headerFamily": "json",
													"language": "json"
												}
											}
										},
										"url": {
											"raw": "{{baseUrl}}/api/employee/:id/",
											"host": [
												"{{baseUrl}}"
											],
											"path": [
												"api",
												"employee",
												":id",
												""
											],
											"variable": [
												{
													"key": "id",
													"value": "8519",
													"description": "(Required) "
												}
											]
										}
									},
									"response": [
										{
											"name": "Untitled Response",
											"originalRequest": {
												"method": "PATCH",
												"header": [
													{
														"key": "Content-Type",
														"value": "application/json"
													},
													{
														"key": "Accept",
														"value": "application/json"
													},
													{
														"key": "Authorization",
														"value": "Bearer <token>",
														"description": "Added as a part of security scheme: bearer"
													}
												],
												"body": {
													"mode": "raw",
													"raw": "{\n  \"fields\": [\n    {\n      \"form_field\": 1000,\n      \"value\": \"string\"\n    },\n    {\n      \"form_field\": 4784,\n      \"value\": \"string\"\n    }\n  ]\n}",
													"options": {
														"raw": {
															"headerFamily": "json",
															"language": "json"
														}
													}
												},
												"url": {
													"raw": "{{baseUrl}}/api/employee/:id/",
													"host": [
														"{{baseUrl}}"
													],
													"path": [
														"api",
														"employee",
														":id",
														""
													],
													"variable": [
														{
															"key": "id"
														}
													]
												}
											},
											"status": "OK",
											"code": 200,
											"_postman_previewlanguage": "json",
											"header": [
												{
													"key": "Content-Type",
													"value": "application/json"
												}
											],
											"cookie": [],
											"body": "{\n  \"fields\": [\n    {\n      \"field_type\": \"s\",\n      \"field_type_name\": \"string\",\n      \"form_field\": 8132,\n      \"label\": \"string\",\n      \"order\": 7990,\n      \"placeholder\": \"string\",\n      \"required\": false,\n      \"value\": \"string\"\n    },\n    {\n      \"field_type\": \"string\",\n      \"field_type_name\": \"string\",\n      \"form_field\": 5410,\n      \"label\": \"string\",\n      \"order\": 3082,\n      \"placeholder\": \"string\",\n      \"required\": false,\n      \"value\": \"string\"\n    }\n  ],\n  \"form_id\": 4667,\n  \"id\": 8594\n}"
										}
									]
								},
								{
									"name": "api employee destroy",
									"request": {
										"auth": {
											"type": "bearer",
											"bearer": [
												{
													"key": "token",
													"value": "{{bearerToken}}",
													"type": "string"
												}
											]
										},
										"method": "DELETE",
										"header": [],
										"url": {
											"raw": "{{baseUrl}}/api/employee/:id/",
											"host": [
												"{{baseUrl}}"
											],
											"path": [
												"api",
												"employee",
												":id",
												""
											],
											"variable": [
												{
													"key": "id",
													"value": "8519",
													"description": "(Required) "
												}
											]
										}
									},
									"response": [
										{
											"name": "No response body",
											"originalRequest": {
												"method": "DELETE",
												"header": [
													{
														"key": "Authorization",
														"value": "Bearer <token>",
														"description": "Added as a part of security scheme: bearer"
													}
												],
												"url": {
													"raw": "{{baseUrl}}/api/employee/:id/",
													"host": [
														"{{baseUrl}}"
													],
													"path": [
														"api",
														"employee",
														":id",
														""
													],
													"variable": [
														{
															"key": "id"
														}
													]
												}
											},
											"status": "No Content",
											"code": 204,
											"_postman_previewlanguage": "text",
											"header": [],
											"cookie": [],
											"body": ""
										}
									]
								}
							]
						},
						{
							"name": "create",
							"item": [
								{
									"name": "api employee create create",
									"request": {
										"auth": {
											"type": "bearer",
											"bearer": [
												{
													"key": "token",
													"value": "{{bearerToken}}",
													"type": "string"
												}
											]
										},
										"method": "POST",
										"header": [
											{
												"key": "Content-Type",
												"value": "application/json"
											},
											{
												"key": "Accept",
												"value": "application/json"
											}
										],
										"body": {
											"mode": "raw",
											"raw": "{\n  \"fields\": [\n    {\n      \"field_id\": 4334,\n      \"value\": \"string\"\n    },\n    {\n      \"field_id\": 2059,\n      \"value\": \"string\"\n    }\n  ],\n  \"form_id\": 1319\n}",
											"options": {
												"raw": {
													"headerFamily": "json",
													"language": "json"
												}
											}
										},
										"url": {
											"raw": "{{baseUrl}}/api/employee/create/",
											"host": [
												"{{baseUrl}}"
											],
											"path": [
												"api",
												"employee",
												"create",
												""
											]
										}
									},
									"response": [
										{
											"name": "Untitled Response",
											"originalRequest": {
												"method": "POST",
												"header": [
													{
														"key": "Content-Type",
														"value": "application/json"
													},
													{
														"key": "Accept",
														"value": "application/json"
													},
													{
														"key": "Authorization",
														"value": "Bearer <token>",
														"description": "Added as a part of security scheme: bearer"
													}
												],
												"body": {
													"mode": "raw",
													"raw": "{\n  \"fields\": [\n    {\n      \"field_id\": 4334,\n      \"value\": \"string\"\n    },\n    {\n      \"field_id\": 2059,\n      \"value\": \"string\"\n    }\n  ],\n  \"form_id\": 1319\n}",
													"options": {
														"raw": {
															"headerFamily": "json",
															"language": "json"
														}
													}
												},
												"url": {
													"raw": "{{baseUrl}}/api/employee/create/",
													"host": [
														"{{baseUrl}}"
													],
													"path": [
														"api",
														"employee",
														"create",
														""
													]
												}
											},
											"status": "Created",
											"code": 201,
											"_postman_previewlanguage": "json",
											"header": [
												{
													"key": "Content-Type",
													"value": "application/json"
												}
											],
											"cookie": [],
											"body": "{\n  \"form_id\": 3711\n}"
										}
									]
								}
							]
						},
						{
							"name": "search",
							"item": [
								{
									"name": "api employee search create",
									"request": {
										"auth": {
											"type": "bearer",
											"bearer": [
												{
													"key": "token",
													"value": "{{bearerToken}}",
													"type": "string"
												}
											]
										},
										"method": "POST",
										"header": [],
										"url": {
											"raw": "{{baseUrl}}/api/employee/search/",
											"host": [
												"{{baseUrl}}"
											],
											"path": [
												"api",
												"employee",
												"search",
												""
											]
										}
									},
									"response": [
										{
											"name": "No response body",
											"originalRequest": {
												"method": "POST",
												"header": [
													{
														"key": "Authorization",
														"value": "Bearer <token>",
														"description": "Added as a part of security scheme: bearer"
													}
												],
												"url": {
													"raw": "{{baseUrl}}/api/employee/search/",
													"host": [
														"{{baseUrl}}"
													],
													"path": [
														"api",
														"employee",
														"search",
														""
													]
												}
											},
											"status": "OK",
											"code": 200,
											"_postman_previewlanguage": "json",
											"header": [
												{
													"key": "Content-Type",
													"value": "application/json",
													"name": "Content-Type",
													"description": "",
													"type": "text"
												}
											],
											"cookie": [],
											"body": "[\r\n    {\r\n        \"id\": \"int\",\r\n        \"form\": \"string\",\r\n        \"created_by\": \"string\",\r\n        \"created_at\": \"datetime\",\r\n        \"fields\": {\r\n            \"Name\": \"string\",\r\n            \"Email\": \"string\",\r\n            \"Mobile\": \"string\",\r\n            \"DOB\": \"string\",\r\n            \"Role\": \"string\",\r\n            \"Password\": \"string\",\r\n            \"Confirm Password\": \"string\"\r\n        }\r\n    }\r\n]"
										}
									]
								}
							]
						}
					]
				},
				{
					"name": "field-types",
					"item": [
						{
							"name": "api field types list",
							"request": {
								"auth": {
									"type": "bearer",
									"bearer": [
										{
											"key": "token",
											"value": "{{bearerToken}}",
											"type": "string"
										}
									]
								},
								"method": "GET",
								"header": [
									{
										"key": "Accept",
										"value": "application/json"
									}
								],
								"url": {
									"raw": "{{baseUrl}}/api/field-types/",
									"host": [
										"{{baseUrl}}"
									],
									"path": [
										"api",
										"field-types",
										""
									]
								}
							},
							"response": [
								{
									"name": "Untitled Response",
									"originalRequest": {
										"method": "GET",
										"header": [
											{
												"key": "Accept",
												"value": "application/json"
											},
											{
												"key": "Authorization",
												"value": "Bearer <token>",
												"description": "Added as a part of security scheme: bearer"
											}
										],
										"url": {
											"raw": "{{baseUrl}}/api/field-types/",
											"host": [
												"{{baseUrl}}"
											],
											"path": [
												"api",
												"field-types",
												""
											]
										}
									},
									"status": "OK",
									"code": 200,
									"_postman_previewlanguage": "json",
									"header": [
										{
											"key": "Content-Type",
											"value": "application/json"
										}
									],
									"cookie": [],
									"body": "[\n  {\n    \"display_name\": \"string\",\n    \"id\": 5962,\n    \"name\": \"string\",\n    \"html_input_type\": \"string\",\n    \"description\": \"string\"\n  },\n  {\n    \"display_name\": \"string\",\n    \"id\": 5464,\n    \"name\": \"string\",\n    \"html_input_type\": \"string\",\n    \"description\": \"st\"\n  }\n]"
								}
							]
						}
					]
				},
				{
					"name": "forms",
					"item": [
						{
							"name": "{id}",
							"item": [
								{
									"name": "api forms retrieve",
									"request": {
										"auth": {
											"type": "bearer",
											"bearer": [
												{
													"key": "token",
													"value": "{{bearerToken}}",
													"type": "string"
												}
											]
										},
										"method": "GET",
										"header": [
											{
												"key": "Accept",
												"value": "application/json"
											}
										],
										"url": {
											"raw": "{{baseUrl}}/api/forms/:id/",
											"host": [
												"{{baseUrl}}"
											],
											"path": [
												"api",
												"forms",
												":id",
												""
											],
											"variable": [
												{
													"key": "id",
													"value": "8519",
													"description": "(Required) "
												}
											]
										}
									},
									"response": [
										{
											"name": "Untitled Response",
											"originalRequest": {
												"method": "GET",
												"header": [
													{
														"key": "Accept",
														"value": "application/json"
													},
													{
														"key": "Authorization",
														"value": "Bearer <token>",
														"description": "Added as a part of security scheme: bearer"
													}
												],
												"url": {
													"raw": "{{baseUrl}}/api/forms/:id/",
													"host": [
														"{{baseUrl}}"
													],
													"path": [
														"api",
														"forms",
														":id",
														""
													],
													"variable": [
														{
															"key": "id"
														}
													]
												}
											},
											"status": "OK",
											"code": 200,
											"_postman_previewlanguage": "json",
											"header": [
												{
													"key": "Content-Type",
													"value": "application/json"
												}
											],
											"cookie": [],
											"body": "{\n  \"created_at\": \"1988-11-19T19:03:48.771Z\",\n  \"fields\": [\n    {\n      \"field_type\": 9787,\n      \"id\": 2043,\n      \"label\": \"string\",\n      \"placeholder\": \"string\",\n      \"required\": true,\n      \"order\": 5812373305842080000\n    },\n    {\n      \"field_type\": 3742,\n      \"id\": 4918,\n      \"label\": \"string\",\n      \"placeholder\": \"string\",\n      \"required\": false,\n      \"order\": 4337912200997497000\n    }\n  ],\n  \"id\": 6274,\n  \"name\": \"string\",\n  \"description\": \"string\"\n}"
										}
									]
								},
								{
									"name": "api forms update",
									"request": {
										"auth": {
											"type": "bearer",
											"bearer": [
												{
													"key": "token",
													"value": "{{bearerToken}}",
													"type": "string"
												}
											]
										},
										"method": "PUT",
										"header": [
											{
												"key": "Content-Type",
												"value": "application/json"
											},
											{
												"key": "Accept",
												"value": "application/json"
											}
										],
										"body": {
											"mode": "raw",
											"raw": "{\n  \"fields\": [\n    {\n      \"field_type\": 4108,\n      \"label\": \"string\",\n      \"placeholder\": \"string\",\n      \"required\": true,\n      \"order\": 7659186976349272000\n    },\n    {\n      \"field_type\": 3265,\n      \"label\": \"string\",\n      \"placeholder\": \"string\",\n      \"required\": true,\n      \"order\": 1848616635788060700\n    }\n  ],\n  \"name\": \"string\",\n  \"description\": \"string\"\n}",
											"options": {
												"raw": {
													"headerFamily": "json",
													"language": "json"
												}
											}
										},
										"url": {
											"raw": "{{baseUrl}}/api/forms/:id/",
											"host": [
												"{{baseUrl}}"
											],
											"path": [
												"api",
												"forms",
												":id",
												""
											],
											"variable": [
												{
													"key": "id",
													"value": "8519",
													"description": "(Required) "
												}
											]
										}
									},
									"response": [
										{
											"name": "Untitled Response",
											"originalRequest": {
												"method": "PUT",
												"header": [
													{
														"key": "Content-Type",
														"value": "application/json"
													},
													{
														"key": "Accept",
														"value": "application/json"
													},
													{
														"key": "Authorization",
														"value": "Bearer <token>",
														"description": "Added as a part of security scheme: bearer"
													}
												],
												"body": {
													"mode": "raw",
													"raw": "{\n  \"fields\": [\n    {\n      \"field_type\": 4108,\n      \"label\": \"string\",\n      \"placeholder\": \"string\",\n      \"required\": true,\n      \"order\": 7659186976349272000\n    },\n    {\n      \"field_type\": 3265,\n      \"label\": \"string\",\n      \"placeholder\": \"string\",\n      \"required\": true,\n      \"order\": 1848616635788060700\n    }\n  ],\n  \"name\": \"string\",\n  \"description\": \"string\"\n}",
													"options": {
														"raw": {
															"headerFamily": "json",
															"language": "json"
														}
													}
												},
												"url": {
													"raw": "{{baseUrl}}/api/forms/:id/",
													"host": [
														"{{baseUrl}}"
													],
													"path": [
														"api",
														"forms",
														":id",
														""
													],
													"variable": [
														{
															"key": "id"
														}
													]
												}
											},
											"status": "OK",
											"code": 200,
											"_postman_previewlanguage": "json",
											"header": [
												{
													"key": "Content-Type",
													"value": "application/json"
												}
											],
											"cookie": [],
											"body": "{\n  \"created_at\": \"1988-11-19T19:03:48.771Z\",\n  \"fields\": [\n    {\n      \"field_type\": 9787,\n      \"id\": 2043,\n      \"label\": \"string\",\n      \"placeholder\": \"string\",\n      \"required\": true,\n      \"order\": 5812373305842080000\n    },\n    {\n      \"field_type\": 3742,\n      \"id\": 4918,\n      \"label\": \"string\",\n      \"placeholder\": \"string\",\n      \"required\": false,\n      \"order\": 4337912200997497000\n    }\n  ],\n  \"id\": 6274,\n  \"name\": \"string\",\n  \"description\": \"string\"\n}"
										}
									]
								},
								{
									"name": "api forms partial update",
									"request": {
										"auth": {
											"type": "bearer",
											"bearer": [
												{
													"key": "token",
													"value": "{{bearerToken}}",
													"type": "string"
												}
											]
										},
										"method": "PATCH",
										"header": [
											{
												"key": "Content-Type",
												"value": "application/json"
											},
											{
												"key": "Accept",
												"value": "application/json"
											}
										],
										"body": {
											"mode": "raw",
											"raw": "{\n  \"name\": \"string\",\n  \"description\": \"string\",\n  \"fields\": [\n    {\n      \"field_type\": 5970,\n      \"label\": \"string\",\n      \"placeholder\": \"string\",\n      \"required\": false,\n      \"order\": 6667307641289366000\n    },\n    {\n      \"field_type\": 2080,\n      \"label\": \"string\",\n      \"placeholder\": \"string\",\n      \"required\": true,\n      \"order\": 689653469270204400\n    }\n  ]\n}",
											"options": {
												"raw": {
													"headerFamily": "json",
													"language": "json"
												}
											}
										},
										"url": {
											"raw": "{{baseUrl}}/api/forms/:id/",
											"host": [
												"{{baseUrl}}"
											],
											"path": [
												"api",
												"forms",
												":id",
												""
											],
											"variable": [
												{
													"key": "id",
													"value": "8519",
													"description": "(Required) "
												}
											]
										}
									},
									"response": [
										{
											"name": "Untitled Response",
											"originalRequest": {
												"method": "PATCH",
												"header": [
													{
														"key": "Content-Type",
														"value": "application/json"
													},
													{
														"key": "Accept",
														"value": "application/json"
													},
													{
														"key": "Authorization",
														"value": "Bearer <token>",
														"description": "Added as a part of security scheme: bearer"
													}
												],
												"body": {
													"mode": "raw",
													"raw": "{\n  \"name\": \"string\",\n  \"description\": \"string\",\n  \"fields\": [\n    {\n      \"field_type\": 5970,\n      \"label\": \"string\",\n      \"placeholder\": \"string\",\n      \"required\": false,\n      \"order\": 6667307641289366000\n    },\n    {\n      \"field_type\": 2080,\n      \"label\": \"string\",\n      \"placeholder\": \"string\",\n      \"required\": true,\n      \"order\": 689653469270204400\n    }\n  ]\n}",
													"options": {
														"raw": {
															"headerFamily": "json",
															"language": "json"
														}
													}
												},
												"url": {
													"raw": "{{baseUrl}}/api/forms/:id/",
													"host": [
														"{{baseUrl}}"
													],
													"path": [
														"api",
														"forms",
														":id",
														""
													],
													"variable": [
														{
															"key": "id"
														}
													]
												}
											},
											"status": "OK",
											"code": 200,
											"_postman_previewlanguage": "json",
											"header": [
												{
													"key": "Content-Type",
													"value": "application/json"
												}
											],
											"cookie": [],
											"body": "{\n  \"created_at\": \"1988-11-19T19:03:48.771Z\",\n  \"fields\": [\n    {\n      \"field_type\": 9787,\n      \"id\": 2043,\n      \"label\": \"string\",\n      \"placeholder\": \"string\",\n      \"required\": true,\n      \"order\": 5812373305842080000\n    },\n    {\n      \"field_type\": 3742,\n      \"id\": 4918,\n      \"label\": \"string\",\n      \"placeholder\": \"string\",\n      \"required\": false,\n      \"order\": 4337912200997497000\n    }\n  ],\n  \"id\": 6274,\n  \"name\": \"string\",\n  \"description\": \"string\"\n}"
										}
									]
								},
								{
									"name": "api forms destroy",
									"request": {
										"auth": {
											"type": "bearer",
											"bearer": [
												{
													"key": "token",
													"value": "{{bearerToken}}",
													"type": "string"
												}
											]
										},
										"method": "DELETE",
										"header": [],
										"url": {
											"raw": "{{baseUrl}}/api/forms/:id/",
											"host": [
												"{{baseUrl}}"
											],
											"path": [
												"api",
												"forms",
												":id",
												""
											],
											"variable": [
												{
													"key": "id",
													"value": "8519",
													"description": "(Required) "
												}
											]
										}
									},
									"response": [
										{
											"name": "No response body",
											"originalRequest": {
												"method": "DELETE",
												"header": [
													{
														"key": "Authorization",
														"value": "Bearer <token>",
														"description": "Added as a part of security scheme: bearer"
													}
												],
												"url": {
													"raw": "{{baseUrl}}/api/forms/:id/",
													"host": [
														"{{baseUrl}}"
													],
													"path": [
														"api",
														"forms",
														":id",
														""
													],
													"variable": [
														{
															"key": "id"
														}
													]
												}
											},
											"status": "No Content",
											"code": 204,
											"_postman_previewlanguage": "text",
											"header": [],
											"cookie": [],
											"body": ""
										}
									]
								}
							]
						},
						{
							"name": "api forms list",
							"request": {
								"auth": {
									"type": "bearer",
									"bearer": [
										{
											"key": "token",
											"value": "{{bearerToken}}",
											"type": "string"
										}
									]
								},
								"method": "GET",
								"header": [
									{
										"key": "Accept",
										"value": "application/json"
									}
								],
								"url": {
									"raw": "{{baseUrl}}/api/forms/",
									"host": [
										"{{baseUrl}}"
									],
									"path": [
										"api",
										"forms",
										""
									]
								}
							},
							"response": [
								{
									"name": "Untitled Response",
									"originalRequest": {
										"method": "GET",
										"header": [
											{
												"key": "Accept",
												"value": "application/json"
											},
											{
												"key": "Authorization",
												"value": "Bearer <token>",
												"description": "Added as a part of security scheme: bearer"
											}
										],
										"url": {
											"raw": "{{baseUrl}}/api/forms/",
											"host": [
												"{{baseUrl}}"
											],
											"path": [
												"api",
												"forms",
												""
											]
										}
									},
									"status": "OK",
									"code": 200,
									"_postman_previewlanguage": "json",
									"header": [
										{
											"key": "Content-Type",
											"value": "application/json"
										}
									],
									"cookie": [],
									"body": "[\n  {\n    \"created_at\": \"2008-05-10T17:20:16.263Z\",\n    \"fields\": [\n      {\n        \"field_type\": 2592,\n        \"id\": 2605,\n        \"label\": \"string\",\n        \"placeholder\": \"string\",\n        \"required\": false,\n        \"order\": 8835498216522078000\n      },\n      {\n        \"field_type\": 5381,\n        \"id\": 9146,\n        \"label\": \"string\",\n        \"placeholder\": \"string\",\n        \"required\": false,\n        \"order\": 7496128650485950000\n      }\n    ],\n    \"id\": 2114,\n    \"name\": \"string\",\n    \"description\": \"string\"\n  },\n  {\n    \"created_at\": \"2022-10-23T16:26:31.764Z\",\n    \"fields\": [\n      {\n        \"field_type\": 1940,\n        \"id\": 9772,\n        \"label\": \"string\",\n        \"placeholder\": \"s\",\n        \"required\": false,\n        \"order\": 5257987923681882000\n      },\n      {\n        \"field_type\": 741,\n        \"id\": 1519,\n        \"label\": \"string\",\n        \"placeholder\": \"string\",\n        \"required\": true,\n        \"order\": 1138783422230040600\n      }\n    ],\n    \"id\": 8139,\n    \"name\": \"st\",\n    \"description\": \"string\"\n  }\n]"
								}
							]
						},
						{
							"name": "api forms create",
							"request": {
								"auth": {
									"type": "bearer",
									"bearer": [
										{
											"key": "token",
											"value": "{{bearerToken}}",
											"type": "string"
										}
									]
								},
								"method": "POST",
								"header": [
									{
										"key": "Content-Type",
										"value": "application/json"
									},
									{
										"key": "Accept",
										"value": "application/json"
									}
								],
								"body": {
									"mode": "raw",
									"raw": "{\n  \"fields\": [\n    {\n      \"field_type\": 4108,\n      \"label\": \"string\",\n      \"placeholder\": \"string\",\n      \"required\": true,\n      \"order\": 7659186976349272000\n    },\n    {\n      \"field_type\": 3265,\n      \"label\": \"string\",\n      \"placeholder\": \"string\",\n      \"required\": true,\n      \"order\": 1848616635788060700\n    }\n  ],\n  \"name\": \"string\",\n  \"description\": \"string\"\n}",
									"options": {
										"raw": {
											"headerFamily": "json",
											"language": "json"
										}
									}
								},
								"url": {
									"raw": "{{baseUrl}}/api/forms/",
									"host": [
										"{{baseUrl}}"
									],
									"path": [
										"api",
										"forms",
										""
									]
								}
							},
							"response": [
								{
									"name": "Untitled Response",
									"originalRequest": {
										"method": "POST",
										"header": [
											{
												"key": "Content-Type",
												"value": "application/json"
											},
											{
												"key": "Accept",
												"value": "application/json"
											},
											{
												"key": "Authorization",
												"value": "Bearer <token>",
												"description": "Added as a part of security scheme: bearer"
											}
										],
										"body": {
											"mode": "raw",
											"raw": "{\n  \"fields\": [\n    {\n      \"field_type\": 4108,\n      \"label\": \"string\",\n      \"placeholder\": \"string\",\n      \"required\": true,\n      \"order\": 7659186976349272000\n    },\n    {\n      \"field_type\": 3265,\n      \"label\": \"string\",\n      \"placeholder\": \"string\",\n      \"required\": true,\n      \"order\": 1848616635788060700\n    }\n  ],\n  \"name\": \"string\",\n  \"description\": \"string\"\n}",
											"options": {
												"raw": {
													"headerFamily": "json",
													"language": "json"
												}
											}
										},
										"url": {
											"raw": "{{baseUrl}}/api/forms/",
											"host": [
												"{{baseUrl}}"
											],
											"path": [
												"api",
												"forms",
												""
											]
										}
									},
									"status": "Created",
									"code": 201,
									"_postman_previewlanguage": "json",
									"header": [
										{
											"key": "Content-Type",
											"value": "application/json"
										}
									],
									"cookie": [],
									"body": "{\n  \"created_at\": \"1988-11-19T19:03:48.771Z\",\n  \"fields\": [\n    {\n      \"field_type\": 9787,\n      \"id\": 2043,\n      \"label\": \"string\",\n      \"placeholder\": \"string\",\n      \"required\": true,\n      \"order\": 5812373305842080000\n    },\n    {\n      \"field_type\": 3742,\n      \"id\": 4918,\n      \"label\": \"string\",\n      \"placeholder\": \"string\",\n      \"required\": false,\n      \"order\": 4337912200997497000\n    }\n  ],\n  \"id\": 6274,\n  \"name\": \"string\",\n  \"description\": \"string\"\n}"
								}
							]
						}
					]
				}
			]
		}
	],
	"variable": [
		{
			"key": "baseUrl",
			"value": "/"
		}
	]
}